__init__.py
display.py
display_image-0.1.8.dist-info/licenses/LICENSE.md
display_image-0.1.8.dist-info/METADATA
display_image-0.1.8.dist-info/WHEEL
display_image-0.1.8.dist-info/entry_points.txt
display_image-0.1.8.dist-info/top_level.txt
display_image-0.1.8.dist-info/RECORD
