Metadata-Version: 2.4
Name: display-image
Version: 0.1.8
Summary:  PyQt6 Gui App to display the wide range image formats (jpg, png, tif, dng, bmp, and RAWs), with image metadata and histogram.
Author-email: Yuan SUN <sunyuan860510@gmail.com>
Maintainer-email: Yuan SUN <sunyuan860510@gmail.com>
License: MIT License
Project-URL: Homepage, https://github.com/sygslhy/display-image
Project-URL: Repository, https://github.com/sygslhy/display-image
Project-URL: Issues, https://github.com/sygslhy/display-image/issues
Project-URL: Releases, https://github.com/sygslhy/display-image/releases
Keywords: display ,image,view,display image,image viewer,raw viewer,display raw image
Classifier: Development Status :: 4 - Beta
Classifier: Programming Language :: Python :: 3
Classifier: Programming Language :: Python :: 3 :: Only
Classifier: License :: OSI Approved :: MIT License
Classifier: Operating System :: Microsoft :: Windows
Classifier: Operating System :: POSIX :: Linux
Classifier: Operating System :: MacOS
Classifier: Topic :: Scientific/Engineering
Classifier: Topic :: Software Development
Classifier: Intended Audience :: Science/Research
Classifier: Intended Audience :: Developers
Requires-Python: >=3.9
License-File: LICENSE.md
Requires-Dist: cxx-image-io>=1.1.3
Requires-Dist: PyQt6>=6.8.0
Requires-Dist: pyqtgraph>=0.13.7
Requires-Dist: QDarkStyle>=3.2.3
Dynamic: license-file
